aws_eden_core/__init__.py
aws_eden_core/methods.py
aws_eden_core/validators.py
aws_eden_core-0.2.0.dist-info/LICENSE
aws_eden_core-0.2.0.dist-info/METADATA
aws_eden_core-0.2.0.dist-info/WHEEL
aws_eden_core-0.2.0.dist-info/top_level.txt
aws_eden_core-0.2.0.dist-info/zip-safe
aws_eden_core-0.2.0.dist-info/RECORD
