Metadata-Version: 2.1
Name: aws-eden-core
Version: 0.2.0
Summary: ECS Dynamic Environment Manager (eden) core package
Home-page: https://github.com/baikonur-oss/aws-eden-core
Author: Tamirlan Torgayev
Author-email: torgayev@me.com
License: MIT
Project-URL: Source Code, https://github.com/baikonur-oss/aws-eden-core
Platform: UNKNOWN
Classifier: Development Status :: 4 - Beta
Classifier: Intended Audience :: Developers
Classifier: License :: OSI Approved :: MIT License
Classifier: Operating System :: OS Independent
Classifier: Programming Language :: Python :: 3
Requires-Dist: boto3
